CHANGES.rst
MANIFEST.in
README.rst
buildout.cfg
requirements-coverage.txt
requirements-tests.txt
setup.py
docs/CONTRIBUTORS.txt
docs/LICENSE.GPL
docs/LICENSE.txt
src/EXTERNALS.txt
src/Products/__init__.py
src/Products.MeetingBEP.egg-info/PKG-INFO
src/Products.MeetingBEP.egg-info/SOURCES.txt
src/Products.MeetingBEP.egg-info/dependency_links.txt
src/Products.MeetingBEP.egg-info/namespace_packages.txt
src/Products.MeetingBEP.egg-info/not-zip-safe
src/Products.MeetingBEP.egg-info/requires.txt
src/Products.MeetingBEP.egg-info/top_level.txt
src/Products/MeetingBEP/__init__.py
src/Products/MeetingBEP/adapters.py
src/Products/MeetingBEP/config.py
src/Products/MeetingBEP/configure.zcml
src/Products/MeetingBEP/interfaces.py
src/Products/MeetingBEP/overrides.zcml
src/Products/MeetingBEP/profiles.zcml
src/Products/MeetingBEP/setuphandlers.py
src/Products/MeetingBEP/testing.py
src/Products/MeetingBEP/testing.zcml
src/Products/MeetingBEP/utils.py
src/Products/MeetingBEP/locales/PloneMeeting.pot
src/Products/MeetingBEP/locales/imio.prettylink.pot
src/Products/MeetingBEP/locales/plone.pot
src/Products/MeetingBEP/locales/sync_pos.sh
src/Products/MeetingBEP/locales/en/LC_MESSAGES/PloneMeeting.po
src/Products/MeetingBEP/locales/en/LC_MESSAGES/imio.prettylink.po
src/Products/MeetingBEP/locales/en/LC_MESSAGES/plone.po
src/Products/MeetingBEP/locales/fr/LC_MESSAGES/PloneMeeting.po
src/Products/MeetingBEP/locales/fr/LC_MESSAGES/imio.prettylink.po
src/Products/MeetingBEP/locales/fr/LC_MESSAGES/plone.po
src/Products/MeetingBEP/migrations/__init__.py
src/Products/MeetingBEP/migrations/migrate_to_4200.py
src/Products/MeetingBEP/migrations/migrate_to_4_1.py
src/Products/MeetingBEP/model/__init__.py
src/Products/MeetingBEP/model/pm_updates.py
src/Products/MeetingBEP/profiles/__init__.py
src/Products/MeetingBEP/profiles/default/MeetingBEP_marker.txt
src/Products/MeetingBEP/profiles/default/__init__.py
src/Products/MeetingBEP/profiles/default/cssregistry.xml
src/Products/MeetingBEP/profiles/default/import_steps.xml
src/Products/MeetingBEP/profiles/default/jsregistry.xml
src/Products/MeetingBEP/profiles/default/metadata.xml
src/Products/MeetingBEP/profiles/default/skins.xml
src/Products/MeetingBEP/profiles/default/toolset.xml
src/Products/MeetingBEP/profiles/testing/MeetingBEP_testing_marker.txt
