Metadata-Version: 2.1
Name: Products.MeetingBEP
Version: 4.2.1
Summary: Official meetings management for BEP (PloneMeeting extension profile)
Home-page: http://www.imio.be/produits/gestion-des-deliberations
Author: Gauthier Bastien
Author-email: gauthier@imio.be
License: GPL
Keywords: plone official meetings management egov communesplone imio plonegov
Platform: UNKNOWN
Classifier: Development Status :: 6 - Mature
Classifier: Environment :: Web Environment
Classifier: Framework :: Plone
Classifier: Framework :: Plone :: 4.3
Classifier: License :: OSI Approved :: GNU General Public License (GPL)
Classifier: Operating System :: OS Independent
Classifier: Programming Language :: Python
Classifier: Programming Language :: Python :: 2.7
Classifier: Topic :: Office/Business
Provides-Extra: test
